tests/__init__.py
tests/test_plot.py
visual_midi/__init__.py
visual_midi/presets.py
visual_midi/visual_midi.py
Visual_MIDI-1.1.0.dist-info/LICENSE
Visual_MIDI-1.1.0.dist-info/METADATA
Visual_MIDI-1.1.0.dist-info/WHEEL
Visual_MIDI-1.1.0.dist-info/entry_points.txt
Visual_MIDI-1.1.0.dist-info/top_level.txt
Visual_MIDI-1.1.0.dist-info/RECORD
