Metadata-Version: 2.1
Name: Visual-MIDI
Version: 1.1.0
Summary: Converts a pretty midi sequence to a boket plot
Home-page: http://packages.python.org/visual_midi
Author: Alexandre DuBreuil
Author-email: code@alexandredubreuil.com
License: MIT License
Keywords: midi,bokeh
Platform: UNKNOWN
Classifier: Development Status :: 3 - Alpha
Classifier: Topic :: Utilities
Classifier: License :: OSI Approved :: MIT License
